{
  "schemaVersion": "2.3",
  "asOf": "2026-03-03T00:00:00-05:00",
  "lastTradingDay": "2026-03-03",
  "prices": {
    "QQQM": {
      "last": 246.6999969482422,
      "prevClose": 250.36000061035156,
      "changePct": -0.014618963305586628
    },
    "XLP": {
      "last": 87.6050033569336,
      "prevClose": 88.70999908447266,
      "changePct": -0.01245627030710313
    },
    "VOO": {
      "last": 622.8599853515625,
      "prevClose": 631.280029296875,
      "changePct": -0.013338048971216175
    },
    "UUP": {
      "last": 27.520000457763672,
      "prevClose": 27.329999923706055,
      "changePct": 0.006952086885767264
    },
    "GLD": {
      "last": 466.67498779296875,
      "prevClose": 490.0,
      "changePct": -0.04760206572863521
    },
    "TNX": {
      "last": 4.060999870300293,
      "prevClose": 4.047999858856201,
      "changePct": 0.0032114653896665566
    },
    "VIX": {
      "last": 24.5,
      "prevClose": 21.440000534057617,
      "changePct": 0.14272385213244507
    }
  },
  "featuresZ": {
    "x": -0.24306141046536658,
    "y": -0.929320915500774,
    "rates": -1.37441213227374,
    "usd": 1.334116537052839,
    "vix": 1.1675111935733191,
    "goldFear": 0.271475357812511
  },
  "daily": {
    "score": 29,
    "Cfinal": 94,
    "regime7": "7C",
    "probs": {
      "1": {
        "p": 0.11375417741713832,
        "c": 23
      },
      "2": {
        "p": 0.45635229397352084,
        "c": 94
      },
      "3": {
        "p": 0.11576054897110524,
        "c": 24
      },
      "4": {
        "p": 0.10507745155891514,
        "c": 22
      },
      "5": {
        "p": 0.08134275040514355,
        "c": 17
      },
      "6": {
        "p": 0.12771277767417696,
        "c": 26
      }
    },
    "caps": {
      "data": false,
      "panic": false,
      "corr": false
    },
    "flags": {
      "Icorr": 0,
      "Ipanic": 0,
      "Idefense": 1
    },
    "vec": [
      -0.24306141046536658,
      -0.929320915500774,
      -1.37441213227374,
      1.334116537052839,
      1.1675111935733191,
      0.271475357812511
    ]
  },
  "periods": {
    "20D": {
      "featuresZ": {
        "x": -0.38538747783007665,
        "y": -2.353106256203415,
        "rates": -0.9215511767751866,
        "usd": 1.4343484010729846,
        "vix": 1.8111632566533187,
        "goldFear": -0.07663088184344402
      },
      "daily": {
        "score": 24,
        "Cfinal": 35,
        "regime7": "7B",
        "probs": {
          "1": {
            "p": 0.0,
            "c": 5
          },
          "2": {
            "p": 1.0,
            "c": 35
          },
          "3": {
            "p": 0.0,
            "c": 5
          },
          "4": {
            "p": 0.0,
            "c": 5
          },
          "5": {
            "p": 0.0,
            "c": 5
          },
          "6": {
            "p": 0.0,
            "c": 5
          }
        },
        "caps": {
          "data": false,
          "panic": true,
          "corr": false
        },
        "flags": {
          "Icorr": 0,
          "Ipanic": 1,
          "Idefense": 1
        },
        "vec": [
          -0.38538747783007665,
          -2.353106256203415,
          -0.9215511767751866,
          1.4343484010729846,
          1.8111632566533187,
          -0.07663088184344402
        ]
      }
    },
    "60D": {
      "featuresZ": {
        "x": -1.400277678463821,
        "y": -2.4441423879697077,
        "rates": -1.944095128660663,
        "usd": 1.9809758617149082,
        "vix": 2.1705663893431533,
        "goldFear": -0.5597286739206648
      },
      "daily": {
        "score": 24,
        "Cfinal": 35,
        "regime7": "7B",
        "probs": {
          "1": {
            "p": 0.0,
            "c": 5
          },
          "2": {
            "p": 1.0,
            "c": 35
          },
          "3": {
            "p": 0.0,
            "c": 5
          },
          "4": {
            "p": 0.0,
            "c": 5
          },
          "5": {
            "p": 0.0,
            "c": 5
          },
          "6": {
            "p": 0.0,
            "c": 5
          }
        },
        "caps": {
          "data": false,
          "panic": true,
          "corr": false
        },
        "flags": {
          "Icorr": 0,
          "Ipanic": 1,
          "Idefense": 1
        },
        "vec": [
          -1.400277678463821,
          -2.4441423879697077,
          -1.944095128660663,
          1.9809758617149082,
          2.1705663893431533,
          -0.5597286739206648
        ]
      }
    },
    "252D": {
      "featuresZ": {
        "x": -0.24306141046536658,
        "y": -0.929320915500774,
        "rates": -1.37441213227374,
        "usd": 1.334116537052839,
        "vix": 1.1675111935733191,
        "goldFear": 0.271475357812511
      },
      "daily": {
        "score": 29,
        "Cfinal": 94,
        "regime7": "7C",
        "probs": {
          "1": {
            "p": 0.11375417741713832,
            "c": 23
          },
          "2": {
            "p": 0.45635229397352084,
            "c": 94
          },
          "3": {
            "p": 0.11576054897110524,
            "c": 24
          },
          "4": {
            "p": 0.10507745155891514,
            "c": 22
          },
          "5": {
            "p": 0.08134275040514355,
            "c": 17
          },
          "6": {
            "p": 0.12771277767417696,
            "c": 26
          }
        },
        "caps": {
          "data": false,
          "panic": false,
          "corr": false
        },
        "flags": {
          "Icorr": 0,
          "Ipanic": 0,
          "Idefense": 1
        },
        "vec": [
          -0.24306141046536658,
          -0.929320915500774,
          -1.37441213227374,
          1.334116537052839,
          1.1675111935733191,
          0.271475357812511
        ]
      }
    }
  },
  "dataHealth": {
    "level": "OK",
    "source": "yfinance"
  },
  "latencyMin": 752.6,
  "fetchedAt": "2026-03-03T12:32:33.977134-05:00"
}