{
  "schemaVersion": "2.3",
  "asOf": "2026-04-15T00:00:00-04:00",
  "lastTradingDay": "2026-04-15",
  "prices": {
    "QQQM": {
      "last": 260.5369873046875,
      "prevClose": 258.7799987792969,
      "changePct": 0.00678950666078753
    },
    "XLP": {
      "last": 81.25499725341797,
      "prevClose": 81.47000122070312,
      "changePct": -0.002639056880614352
    },
    "VOO": {
      "last": 641.1599731445312,
      "prevClose": 638.3499755859375,
      "changePct": 0.00440197018260159
    },
    "UUP": {
      "last": 27.295000076293945,
      "prevClose": 27.31999969482422,
      "changePct": -0.0009150665742873205
    },
    "GLD": {
      "last": 441.0,
      "prevClose": 445.0899963378906,
      "changePct": -0.009189144603433638
    },
    "TNX": {
      "last": 4.2829999923706055,
      "prevClose": 4.25600004196167,
      "changePct": 0.00634397324782233
    },
    "VIX": {
      "last": 18.209999084472656,
      "prevClose": 18.360000610351562,
      "changePct": -0.008170017477795388
    }
  },
  "featuresZ": {
    "x": 0.8792552608975489,
    "y": 0.7238848245639729,
    "rates": 0.5150828703723126,
    "usd": -0.866624912655505,
    "vix": -0.8906652675796768,
    "goldFear": -0.7531527007738791
  },
  "daily": {
    "score": 58,
    "Cfinal": 96,
    "regime7": "--",
    "probs": {
      "1": {
        "p": 0.0,
        "c": 5
      },
      "2": {
        "p": 0.0,
        "c": 5
      },
      "3": {
        "p": 0.39614077228758793,
        "c": 63
      },
      "4": {
        "p": 0.0,
        "c": 5
      },
      "5": {
        "p": 0.6038592277124121,
        "c": 96
      },
      "6": {
        "p": 0.0,
        "c": 5
      }
    },
    "caps": {
      "data": false,
      "panic": false,
      "corr": false
    },
    "flags": {
      "Icorr": 0,
      "Ipanic": 0,
      "Idefense": 0
    },
    "vec": [
      0.8792552608975489,
      0.7238848245639729,
      0.5150828703723126,
      -0.866624912655505,
      -0.8906652675796768,
      -0.7531527007738791
    ]
  },
  "periods": {
    "20D": {
      "featuresZ": {
        "x": 2.2680271123846927,
        "y": 1.8287467408585758,
        "rates": -1.0911452746220651,
        "usd": -1.6894495942220493,
        "vix": -0.5400561211206453,
        "goldFear": 2.166718143593955
      },
      "daily": {
        "score": 54,
        "Cfinal": 100,
        "regime7": "--",
        "probs": {
          "1": {
            "p": 0.0,
            "c": 5
          },
          "2": {
            "p": 0.0,
            "c": 5
          },
          "3": {
            "p": 0.0,
            "c": 5
          },
          "4": {
            "p": 0.5427642363806618,
            "c": 100
          },
          "5": {
            "p": 0.45723576361933815,
            "c": 84
          },
          "6": {
            "p": 0.0,
            "c": 5
          }
        },
        "caps": {
          "data": false,
          "panic": false,
          "corr": false
        },
        "flags": {
          "Icorr": 0,
          "Ipanic": 0,
          "Idefense": 0
        },
        "vec": [
          2.2680271123846927,
          1.8287467408585758,
          -1.0911452746220651,
          -1.6894495942220493,
          -0.5400561211206453,
          2.166718143593955
        ]
      }
    },
    "60D": {
      "featuresZ": {
        "x": 2.2314558356552556,
        "y": 2.1879223865011426,
        "rates": 0.12370748381468907,
        "usd": -1.207076652792997,
        "vix": -1.0663248764432671,
        "goldFear": 0.007897673725399956
      },
      "daily": {
        "score": 100,
        "Cfinal": 100,
        "regime7": "--",
        "probs": {
          "1": {
            "p": 0.0,
            "c": 5
          },
          "2": {
            "p": 0.0,
            "c": 5
          },
          "3": {
            "p": 0.0,
            "c": 5
          },
          "4": {
            "p": 0.0,
            "c": 5
          },
          "5": {
            "p": 1.0,
            "c": 100
          },
          "6": {
            "p": 0.0,
            "c": 5
          }
        },
        "caps": {
          "data": false,
          "panic": false,
          "corr": false
        },
        "flags": {
          "Icorr": 0,
          "Ipanic": 0,
          "Idefense": 0
        },
        "vec": [
          2.2314558356552556,
          2.1879223865011426,
          0.12370748381468907,
          -1.207076652792997,
          -1.0663248764432671,
          0.007897673725399956
        ]
      }
    },
    "252D": {
      "featuresZ": {
        "x": 0.8792552608975489,
        "y": 0.7238848245639729,
        "rates": 0.5150828703723126,
        "usd": -0.866624912655505,
        "vix": -0.8906652675796768,
        "goldFear": -0.7531527007738791
      },
      "daily": {
        "score": 58,
        "Cfinal": 96,
        "regime7": "--",
        "probs": {
          "1": {
            "p": 0.0,
            "c": 5
          },
          "2": {
            "p": 0.0,
            "c": 5
          },
          "3": {
            "p": 0.39614077228758793,
            "c": 63
          },
          "4": {
            "p": 0.0,
            "c": 5
          },
          "5": {
            "p": 0.6038592277124121,
            "c": 96
          },
          "6": {
            "p": 0.0,
            "c": 5
          }
        },
        "caps": {
          "data": false,
          "panic": false,
          "corr": false
        },
        "flags": {
          "Icorr": 0,
          "Ipanic": 0,
          "Idefense": 0
        },
        "vec": [
          0.8792552608975489,
          0.7238848245639729,
          0.5150828703723126,
          -0.866624912655505,
          -0.8906652675796768,
          -0.7531527007738791
        ]
      }
    }
  },
  "dataHealth": {
    "level": "OK",
    "source": "yfinance"
  },
  "latencyMin": 798.5,
  "fetchedAt": "2026-04-15T13:18:30.865429-04:00"
}