{
  "schemaVersion": "2.3",
  "asOf": "2026-05-06T00:00:00-04:00",
  "lastTradingDay": "2026-05-06",
  "prices": {
    "QQQM": {
      "last": 285.7300109863281,
      "prevClose": 280.6199951171875,
      "changePct": 0.01820973543601792
    },
    "XLP": {
      "last": 84.2750015258789,
      "prevClose": 84.05999755859375,
      "changePct": 0.0025577441533386723
    },
    "VOO": {
      "last": 673.97998046875,
      "prevClose": 665.2999877929688,
      "changePct": 0.013046735059436574
    },
    "UUP": {
      "last": 27.354999542236328,
      "prevClose": 27.5,
      "changePct": -0.005272743918678977
    },
    "GLD": {
      "last": 430.3450012207031,
      "prevClose": 418.2699890136719,
      "changePct": 0.02886894236783638
    },
    "TNX": {
      "last": 4.354000091552734,
      "prevClose": 4.415999889373779,
      "changePct": -0.014039809640900363
    },
    "VIX": {
      "last": 17.139999389648438,
      "prevClose": 17.3799991607666,
      "changePct": -0.013808963331824355
    }
  },
  "featuresZ": {
    "x": 1.5691519628737376,
    "y": 1.6619997668260342,
    "rates": 0.4135812781254916,
    "usd": -0.6174081067602842,
    "vix": -0.6637997099651147,
    "goldFear": -0.34532535264909486
  },
  "daily": {
    "score": 100,
    "Cfinal": 100,
    "regime7": "--",
    "probs": {
      "1": {
        "p": 0.0,
        "c": 5
      },
      "2": {
        "p": 0.0,
        "c": 5
      },
      "3": {
        "p": 0.0,
        "c": 5
      },
      "4": {
        "p": 0.0,
        "c": 5
      },
      "5": {
        "p": 1.0,
        "c": 100
      },
      "6": {
        "p": 0.0,
        "c": 5
      }
    },
    "caps": {
      "data": false,
      "panic": false,
      "corr": false
    },
    "flags": {
      "Icorr": 0,
      "Ipanic": 0,
      "Idefense": 0
    },
    "vec": [
      1.5691519628737376,
      1.6619997668260342,
      0.4135812781254916,
      -0.6174081067602842,
      -0.6637997099651147,
      -0.34532535264909486
    ]
  },
  "periods": {
    "20D": {
      "featuresZ": {
        "x": 1.6247524586165167,
        "y": 0.21686522544851175,
        "rates": 0.6540422524546481,
        "usd": 0.9736022839296213,
        "vix": -0.17895722810529047,
        "goldFear": -0.6795715649967582
      },
      "daily": {
        "score": 94,
        "Cfinal": 94,
        "regime7": "--",
        "probs": {
          "1": {
            "p": 0.0,
            "c": 5
          },
          "2": {
            "p": 0.0,
            "c": 5
          },
          "3": {
            "p": 1.0,
            "c": 94
          },
          "4": {
            "p": 0.0,
            "c": 5
          },
          "5": {
            "p": 0.0,
            "c": 5
          },
          "6": {
            "p": 0.0,
            "c": 5
          }
        },
        "caps": {
          "data": false,
          "panic": false,
          "corr": false
        },
        "flags": {
          "Icorr": 0,
          "Ipanic": 0,
          "Idefense": 0
        },
        "vec": [
          1.6247524586165167,
          0.21686522544851175,
          0.6540422524546481,
          0.9736022839296213,
          -0.17895722810529047,
          -0.6795715649967582
        ]
      }
    },
    "60D": {
      "featuresZ": {
        "x": 2.066059007242022,
        "y": 1.381414879599294,
        "rates": 0.13508927181967115,
        "usd": -0.6681524173655026,
        "vix": -0.6486082630313208,
        "goldFear": 0.34015479588978476
      },
      "daily": {
        "score": 100,
        "Cfinal": 100,
        "regime7": "--",
        "probs": {
          "1": {
            "p": 0.0,
            "c": 5
          },
          "2": {
            "p": 0.0,
            "c": 5
          },
          "3": {
            "p": 0.0,
            "c": 5
          },
          "4": {
            "p": 0.0,
            "c": 5
          },
          "5": {
            "p": 1.0,
            "c": 100
          },
          "6": {
            "p": 0.0,
            "c": 5
          }
        },
        "caps": {
          "data": false,
          "panic": false,
          "corr": false
        },
        "flags": {
          "Icorr": 0,
          "Ipanic": 0,
          "Idefense": 0
        },
        "vec": [
          2.066059007242022,
          1.381414879599294,
          0.13508927181967115,
          -0.6681524173655026,
          -0.6486082630313208,
          0.34015479588978476
        ]
      }
    },
    "252D": {
      "featuresZ": {
        "x": 1.5691519628737376,
        "y": 1.6619997668260342,
        "rates": 0.4135812781254916,
        "usd": -0.6174081067602842,
        "vix": -0.6637997099651147,
        "goldFear": -0.34532535264909486
      },
      "daily": {
        "score": 100,
        "Cfinal": 100,
        "regime7": "--",
        "probs": {
          "1": {
            "p": 0.0,
            "c": 5
          },
          "2": {
            "p": 0.0,
            "c": 5
          },
          "3": {
            "p": 0.0,
            "c": 5
          },
          "4": {
            "p": 0.0,
            "c": 5
          },
          "5": {
            "p": 1.0,
            "c": 100
          },
          "6": {
            "p": 0.0,
            "c": 5
          }
        },
        "caps": {
          "data": false,
          "panic": false,
          "corr": false
        },
        "flags": {
          "Icorr": 0,
          "Ipanic": 0,
          "Idefense": 0
        },
        "vec": [
          1.5691519628737376,
          1.6619997668260342,
          0.4135812781254916,
          -0.6174081067602842,
          -0.6637997099651147,
          -0.34532535264909486
        ]
      }
    }
  },
  "dataHealth": {
    "level": "OK",
    "source": "yfinance"
  },
  "latencyMin": 897.3,
  "fetchedAt": "2026-05-06T14:57:20.156881-04:00"
}