{
  "schemaVersion": "2.3",
  "asOf": "2026-03-20T00:00:00-04:00",
  "lastTradingDay": "2026-03-20",
  "prices": {
    "QQQM": {
      "last": 241.69000244140625,
      "prevClose": 244.1999969482422,
      "changePct": -0.010278437912380183
    },
    "XLP": {
      "last": 81.65499877929688,
      "prevClose": 81.97000122070312,
      "changePct": -0.0038428990693572173
    },
    "VOO": {
      "last": 602.219970703125,
      "prevClose": 606.75,
      "changePct": -0.0074660557014833125
    },
    "UUP": {
      "last": 27.719999313354492,
      "prevClose": 27.579999923706055,
      "changePct": 0.005076120015798213
    },
    "GLD": {
      "last": 418.4700012207031,
      "prevClose": 426.4100036621094,
      "changePct": -0.018620582006087197
    },
    "TNX": {
      "last": 4.381999969482422,
      "prevClose": 4.281000137329102,
      "changePct": 0.023592578582894812
    },
    "VIX": {
      "last": 25.799999237060547,
      "prevClose": 24.059999465942383,
      "changePct": 0.07231919408731424
    }
  },
  "featuresZ": {
    "x": 0.15523713510087433,
    "y": -1.6724318442389368,
    "rates": 2.399414965462231,
    "usd": 1.388810709354686,
    "vix": -0.3447068541749561,
    "goldFear": -3.674741780007799
  },
  "daily": {
    "score": 23,
    "Cfinal": 84,
    "regime7": "7C",
    "probs": {
      "1": {
        "p": 0.2289905209983743,
        "c": 69
      },
      "2": {
        "p": 0.23625446548710613,
        "c": 71
      },
      "3": {
        "p": 0.2777800177571074,
        "c": 84
      },
      "4": {
        "p": 0.05025725997097757,
        "c": 15
      },
      "5": {
        "p": 0.08199063344487015,
        "c": 25
      },
      "6": {
        "p": 0.12472710234156449,
        "c": 38
      }
    },
    "caps": {
      "data": false,
      "panic": false,
      "corr": false
    },
    "flags": {
      "Icorr": 0,
      "Ipanic": 0,
      "Idefense": 0
    },
    "vec": [
      0.15523713510087433,
      -1.6724318442389368,
      2.399414965462231,
      1.388810709354686,
      -0.3447068541749561,
      -3.674741780007799
    ]
  },
  "periods": {
    "20D": {
      "featuresZ": {
        "x": 1.1844335473725998,
        "y": -2.45436545651379,
        "rates": 1.8821689974561746,
        "usd": 0.19081252876239893,
        "vix": -0.7261386265950236,
        "goldFear": -2.507167443438537
      },
      "daily": {
        "score": 90,
        "Cfinal": 90,
        "regime7": "--",
        "probs": {
          "1": {
            "p": 0.0,
            "c": 5
          },
          "2": {
            "p": 0.0,
            "c": 5
          },
          "3": {
            "p": 1.0,
            "c": 90
          },
          "4": {
            "p": 0.0,
            "c": 5
          },
          "5": {
            "p": 0.0,
            "c": 5
          },
          "6": {
            "p": 0.0,
            "c": 5
          }
        },
        "caps": {
          "data": false,
          "panic": false,
          "corr": false
        },
        "flags": {
          "Icorr": 0,
          "Ipanic": 0,
          "Idefense": 0
        },
        "vec": [
          1.1844335473725998,
          -2.45436545651379,
          1.8821689974561746,
          0.19081252876239893,
          -0.7261386265950236,
          -2.507167443438537
        ]
      }
    },
    "60D": {
      "featuresZ": {
        "x": -0.28121478365644315,
        "y": -2.8251656657985733,
        "rates": 2.2147585602829936,
        "usd": 1.2184466752909053,
        "vix": -0.7379275483249549,
        "goldFear": -3.4781838383895245
      },
      "daily": {
        "score": 76,
        "Cfinal": 90,
        "regime7": "--",
        "probs": {
          "1": {
            "p": 1.0,
            "c": 90
          },
          "2": {
            "p": 0.0,
            "c": 5
          },
          "3": {
            "p": 0.0,
            "c": 5
          },
          "4": {
            "p": 0.0,
            "c": 5
          },
          "5": {
            "p": 0.0,
            "c": 5
          },
          "6": {
            "p": 0.0,
            "c": 5
          }
        },
        "caps": {
          "data": false,
          "panic": false,
          "corr": false
        },
        "flags": {
          "Icorr": 0,
          "Ipanic": 0,
          "Idefense": 1
        },
        "vec": [
          -0.28121478365644315,
          -2.8251656657985733,
          2.2147585602829936,
          1.2184466752909053,
          -0.7379275483249549,
          -3.4781838383895245
        ]
      }
    },
    "252D": {
      "featuresZ": {
        "x": 0.15523713510087433,
        "y": -1.6724318442389368,
        "rates": 2.399414965462231,
        "usd": 1.388810709354686,
        "vix": -0.3447068541749561,
        "goldFear": -3.674741780007799
      },
      "daily": {
        "score": 23,
        "Cfinal": 84,
        "regime7": "7C",
        "probs": {
          "1": {
            "p": 0.2289905209983743,
            "c": 69
          },
          "2": {
            "p": 0.23625446548710613,
            "c": 71
          },
          "3": {
            "p": 0.2777800177571074,
            "c": 84
          },
          "4": {
            "p": 0.05025725997097757,
            "c": 15
          },
          "5": {
            "p": 0.08199063344487015,
            "c": 25
          },
          "6": {
            "p": 0.12472710234156449,
            "c": 38
          }
        },
        "caps": {
          "data": false,
          "panic": false,
          "corr": false
        },
        "flags": {
          "Icorr": 0,
          "Ipanic": 0,
          "Idefense": 0
        },
        "vec": [
          0.15523713510087433,
          -1.6724318442389368,
          2.399414965462231,
          1.388810709354686,
          -0.3447068541749561,
          -3.674741780007799
        ]
      }
    }
  },
  "dataHealth": {
    "level": "OK",
    "source": "yfinance"
  },
  "latencyMin": 717.3,
  "fetchedAt": "2026-03-20T11:57:20.880948-04:00"
}