{
  "schemaVersion": "2.3",
  "asOf": "2026-04-07T00:00:00-04:00",
  "lastTradingDay": "2026-04-07",
  "prices": {
    "QQQM": {
      "last": 239.8800048828125,
      "prevClose": 242.32000732421875,
      "changePct": -0.010069339582602362
    },
    "XLP": {
      "last": 82.33000183105469,
      "prevClose": 82.66000366210938,
      "changePct": -0.0039922794148865666
    },
    "VOO": {
      "last": 601.2000122070312,
      "prevClose": 605.6699829101562,
      "changePct": -0.007380208412587066
    },
    "UUP": {
      "last": 27.825000762939453,
      "prevClose": 27.829999923706055,
      "changePct": -0.00017963207978104214
    },
    "GLD": {
      "last": 425.9599914550781,
      "prevClose": 427.6499938964844,
      "changePct": -0.003951835532623267
    },
    "TNX": {
      "last": 4.361999988555908,
      "prevClose": 4.335000038146973,
      "changePct": 0.006228362207922118
    },
    "VIX": {
      "last": 25.899999618530273,
      "prevClose": 24.170000076293945,
      "changePct": 0.07157631513345009
    }
  },
  "featuresZ": {
    "x": -0.11572574898397066,
    "y": -1.2182524285707985,
    "rates": 1.5475612457504966,
    "usd": 0.7198164494482762,
    "vix": -0.8634066023529536,
    "goldFear": -2.5764187943231187
  },
  "daily": {
    "score": 76,
    "Cfinal": 90,
    "regime7": "--",
    "probs": {
      "1": {
        "p": 1.0,
        "c": 90
      },
      "2": {
        "p": 0.0,
        "c": 5
      },
      "3": {
        "p": 0.0,
        "c": 5
      },
      "4": {
        "p": 0.0,
        "c": 5
      },
      "5": {
        "p": 0.0,
        "c": 5
      },
      "6": {
        "p": 0.0,
        "c": 5
      }
    },
    "caps": {
      "data": false,
      "panic": false,
      "corr": false
    },
    "flags": {
      "Icorr": 0,
      "Ipanic": 0,
      "Idefense": 1
    },
    "vec": [
      -0.11572574898397066,
      -1.2182524285707985,
      1.5475612457504966,
      0.7198164494482762,
      -0.8634066023529536,
      -2.5764187943231187
    ]
  },
  "periods": {
    "20D": {
      "featuresZ": {
        "x": -0.37870287335375136,
        "y": 0.3831472572955507,
        "rates": -0.023659424178689676,
        "usd": -1.216768785835184,
        "vix": -1.3206392854255462,
        "goldFear": 0.2090310136423038
      },
      "daily": {
        "score": 31,
        "Cfinal": 94,
        "regime7": "7C",
        "probs": {
          "1": {
            "p": 0.1678664237817664,
            "c": 48
          },
          "2": {
            "p": 0.02723370366811949,
            "c": 8
          },
          "3": {
            "p": 0.09247104953728781,
            "c": 27
          },
          "4": {
            "p": 0.24600223210971012,
            "c": 71
          },
          "5": {
            "p": 0.32676020533389827,
            "c": 94
          },
          "6": {
            "p": 0.13966638556921787,
            "c": 40
          }
        },
        "caps": {
          "data": false,
          "panic": false,
          "corr": false
        },
        "flags": {
          "Icorr": 0,
          "Ipanic": 0,
          "Idefense": 0
        },
        "vec": [
          -0.37870287335375136,
          0.3831472572955507,
          -0.023659424178689676,
          -1.216768785835184,
          -1.3206392854255462,
          0.2090310136423038
        ]
      }
    },
    "60D": {
      "featuresZ": {
        "x": -0.33307433154041677,
        "y": -0.8696674921713774,
        "rates": 0.9909205828063369,
        "usd": 0.30946169394360035,
        "vix": -1.5793221801587045,
        "goldFear": -1.536487409555983
      },
      "daily": {
        "score": 76,
        "Cfinal": 90,
        "regime7": "--",
        "probs": {
          "1": {
            "p": 1.0,
            "c": 90
          },
          "2": {
            "p": 0.0,
            "c": 5
          },
          "3": {
            "p": 0.0,
            "c": 5
          },
          "4": {
            "p": 0.0,
            "c": 5
          },
          "5": {
            "p": 0.0,
            "c": 5
          },
          "6": {
            "p": 0.0,
            "c": 5
          }
        },
        "caps": {
          "data": false,
          "panic": false,
          "corr": false
        },
        "flags": {
          "Icorr": 0,
          "Ipanic": 0,
          "Idefense": 1
        },
        "vec": [
          -0.33307433154041677,
          -0.8696674921713774,
          0.9909205828063369,
          0.30946169394360035,
          -1.5793221801587045,
          -1.536487409555983
        ]
      }
    },
    "252D": {
      "featuresZ": {
        "x": -0.11572574898397066,
        "y": -1.2182524285707985,
        "rates": 1.5475612457504966,
        "usd": 0.7198164494482762,
        "vix": -0.8634066023529536,
        "goldFear": -2.5764187943231187
      },
      "daily": {
        "score": 76,
        "Cfinal": 90,
        "regime7": "--",
        "probs": {
          "1": {
            "p": 1.0,
            "c": 90
          },
          "2": {
            "p": 0.0,
            "c": 5
          },
          "3": {
            "p": 0.0,
            "c": 5
          },
          "4": {
            "p": 0.0,
            "c": 5
          },
          "5": {
            "p": 0.0,
            "c": 5
          },
          "6": {
            "p": 0.0,
            "c": 5
          }
        },
        "caps": {
          "data": false,
          "panic": false,
          "corr": false
        },
        "flags": {
          "Icorr": 0,
          "Ipanic": 0,
          "Idefense": 1
        },
        "vec": [
          -0.11572574898397066,
          -1.2182524285707985,
          1.5475612457504966,
          0.7198164494482762,
          -0.8634066023529536,
          -2.5764187943231187
        ]
      }
    }
  },
  "dataHealth": {
    "level": "OK",
    "source": "yfinance"
  },
  "latencyMin": 600.1,
  "fetchedAt": "2026-04-07T10:00:04.413902-04:00"
}