{
  "schemaVersion": "2.3",
  "asOf": "2026-02-27T00:00:00-05:00",
  "lastTradingDay": "2026-02-27",
  "prices": {
    "QQQM": {
      "last": 250.8800048828125,
      "prevClose": 253.8300018310547,
      "changePct": -0.011621939593278102
    },
    "XLP": {
      "last": 88.86000061035156,
      "prevClose": 89.01000213623047,
      "changePct": -0.0016852210120086033
    },
    "VOO": {
      "last": 633.9500122070312,
      "prevClose": 637.530029296875,
      "changePct": -0.005615448567641766
    },
    "UUP": {
      "last": 27.100000381469727,
      "prevClose": 27.079999923706055,
      "changePct": 0.0007385693434276309
    },
    "GLD": {
      "last": 477.4800109863281,
      "prevClose": 473.4200134277344,
      "changePct": 0.00857588915432172
    },
    "TNX": {
      "last": 3.9830002784729004,
      "prevClose": 4.017000198364258,
      "changePct": -0.008464007521135387
    },
    "VIX": {
      "last": 21.219999313354492,
      "prevClose": 18.6299991607666,
      "changePct": 0.13902309550513772
    }
  },
  "featuresZ": {
    "x": -0.20901034328569035,
    "y": -0.5066955735345438,
    "rates": -1.5174666362713662,
    "usd": 1.2474794851762883,
    "vix": -0.4812014157354599,
    "goldFear": -2.267173454527743
  },
  "daily": {
    "score": 6,
    "Cfinal": 78,
    "regime7": "7C",
    "probs": {
      "1": {
        "p": 0.1669803064389063,
        "c": 58
      },
      "2": {
        "p": 0.22570717661657436,
        "c": 78
      },
      "3": {
        "p": 0.17061294046745357,
        "c": 59
      },
      "4": {
        "p": 0.1950163593249335,
        "c": 67
      },
      "5": {
        "p": 0.1485893931994388,
        "c": 51
      },
      "6": {
        "p": 0.09309382395269356,
        "c": 32
      }
    },
    "caps": {
      "data": false,
      "panic": false,
      "corr": false
    },
    "flags": {
      "Icorr": 0,
      "Ipanic": 0,
      "Idefense": 1
    },
    "vec": [
      -0.20901034328569035,
      -0.5066955735345438,
      -1.5174666362713662,
      1.2474794851762883,
      -0.4812014157354599,
      -2.267173454527743
    ]
  },
  "periods": {
    "20D": {
      "featuresZ": {
        "x": -0.5248278230474535,
        "y": -0.6717736944655406,
        "rates": -1.4441621344880988,
        "usd": 1.8939590434743534,
        "vix": -1.2938080182874185,
        "goldFear": -2.9151788784435313
      },
      "daily": {
        "score": 7,
        "Cfinal": 84,
        "regime7": "7C",
        "probs": {
          "1": {
            "p": 0.19022771837530153,
            "c": 69
          },
          "2": {
            "p": 0.23124356311015284,
            "c": 84
          },
          "3": {
            "p": 0.1809289154614351,
            "c": 66
          },
          "4": {
            "p": 0.16326409516086024,
            "c": 59
          },
          "5": {
            "p": 0.13394310511811672,
            "c": 49
          },
          "6": {
            "p": 0.10039260277413363,
            "c": 36
          }
        },
        "caps": {
          "data": false,
          "panic": false,
          "corr": false
        },
        "flags": {
          "Icorr": 0,
          "Ipanic": 0,
          "Idefense": 1
        },
        "vec": [
          -0.5248278230474535,
          -0.6717736944655406,
          -1.4441621344880988,
          1.8939590434743534,
          -1.2938080182874185,
          -2.9151788784435313
        ]
      }
    },
    "60D": {
      "featuresZ": {
        "x": -1.5405143388588682,
        "y": -1.3470483290039508,
        "rates": -2.5105535013702376,
        "usd": 2.107921169758947,
        "vix": -0.7640134446695839,
        "goldFear": -3.367695291962967
      },
      "daily": {
        "score": 13,
        "Cfinal": 80,
        "regime7": "7C",
        "probs": {
          "1": {
            "p": 0.1799388084674947,
            "c": 45
          },
          "2": {
            "p": 0.31863827236182973,
            "c": 80
          },
          "3": {
            "p": 0.12365706384037198,
            "c": 31
          },
          "4": {
            "p": 0.16530415665701528,
            "c": 42
          },
          "5": {
            "p": 0.11693226048649291,
            "c": 29
          },
          "6": {
            "p": 0.0955294381867953,
            "c": 24
          }
        },
        "caps": {
          "data": false,
          "panic": false,
          "corr": false
        },
        "flags": {
          "Icorr": 0,
          "Ipanic": 0,
          "Idefense": 1
        },
        "vec": [
          -1.5405143388588682,
          -1.3470483290039508,
          -2.5105535013702376,
          2.107921169758947,
          -0.7640134446695839,
          -3.367695291962967
        ]
      }
    },
    "252D": {
      "featuresZ": {
        "x": -0.20901034328569035,
        "y": -0.5066955735345438,
        "rates": -1.5174666362713662,
        "usd": 1.2474794851762883,
        "vix": -0.4812014157354599,
        "goldFear": -2.267173454527743
      },
      "daily": {
        "score": 6,
        "Cfinal": 78,
        "regime7": "7C",
        "probs": {
          "1": {
            "p": 0.1669803064389063,
            "c": 58
          },
          "2": {
            "p": 0.22570717661657436,
            "c": 78
          },
          "3": {
            "p": 0.17061294046745357,
            "c": 59
          },
          "4": {
            "p": 0.1950163593249335,
            "c": 67
          },
          "5": {
            "p": 0.1485893931994388,
            "c": 51
          },
          "6": {
            "p": 0.09309382395269356,
            "c": 32
          }
        },
        "caps": {
          "data": false,
          "panic": false,
          "corr": false
        },
        "flags": {
          "Icorr": 0,
          "Ipanic": 0,
          "Idefense": 1
        },
        "vec": [
          -0.20901034328569035,
          -0.5066955735345438,
          -1.5174666362713662,
          1.2474794851762883,
          -0.4812014157354599,
          -2.267173454527743
        ]
      }
    }
  },
  "dataHealth": {
    "level": "OK",
    "source": "yfinance"
  },
  "latencyMin": 569.0,
  "fetchedAt": "2026-02-27T09:29:02.618996-05:00"
}