{
  "schemaVersion": "2.3",
  "asOf": "2026-02-25T00:00:00-05:00",
  "lastTradingDay": "2026-02-25",
  "prices": {
    "QQQM": {
      "last": 253.61000061035156,
      "prevClose": 250.30999755859375,
      "changePct": 0.013183664591684286
    },
    "XLP": {
      "last": 88.74500274658203,
      "prevClose": 89.73999786376953,
      "changePct": -0.011087532213873682
    },
    "VOO": {
      "last": 637.2799072265625,
      "prevClose": 632.2100219726562,
      "changePct": 0.00801930541703043
    },
    "UUP": {
      "last": 27.070100784301758,
      "prevClose": 27.110000610351562,
      "changePct": -0.0014717751808006052
    },
    "GLD": {
      "last": 476.7900085449219,
      "prevClose": 474.6099853515625,
      "changePct": 0.0045932939901054655
    },
    "TNX": {
      "last": 4.047999858856201,
      "prevClose": 4.0329999923706055,
      "changePct": 0.0037192825474762154
    },
    "VIX": {
      "last": 18.049999237060547,
      "prevClose": 19.549999237060547,
      "changePct": -0.07672634570524585
    }
  },
  "featuresZ": {
    "x": -0.09290498716475099,
    "y": -0.38516396112135887,
    "rates": -1.0976287354713845,
    "usd": 1.550493697661166,
    "vix": -0.49145908461993637,
    "goldFear": -1.6981992116014246
  },
  "daily": {
    "score": 6,
    "Cfinal": 78,
    "regime7": "7C",
    "probs": {
      "1": {
        "p": 0.17464051748295356,
        "c": 60
      },
      "2": {
        "p": 0.2272029223999252,
        "c": 78
      },
      "3": {
        "p": 0.2016494699019724,
        "c": 69
      },
      "4": {
        "p": 0.1581075409993181,
        "c": 54
      },
      "5": {
        "p": 0.13320328611032925,
        "c": 46
      },
      "6": {
        "p": 0.10519626310550151,
        "c": 36
      }
    },
    "caps": {
      "data": false,
      "panic": false,
      "corr": false
    },
    "flags": {
      "Icorr": 0,
      "Ipanic": 0,
      "Idefense": 1
    },
    "vec": [
      -0.09290498716475099,
      -0.38516396112135887,
      -1.0976287354713845,
      1.550493697661166,
      -0.49145908461993637,
      -1.6981992116014246
    ]
  },
  "periods": {
    "20D": {
      "featuresZ": {
        "x": -0.2948377927363878,
        "y": -0.2511194790392795,
        "rates": -1.1276806336159881,
        "usd": 2.6811331195360566,
        "vix": -1.3703187683887121,
        "goldFear": -2.817648298182603
      },
      "daily": {
        "score": 5,
        "Cfinal": 78,
        "regime7": "7C",
        "probs": {
          "1": {
            "p": 0.19140019112418363,
            "c": 68
          },
          "2": {
            "p": 0.22004947186126006,
            "c": 78
          },
          "3": {
            "p": 0.2190868385526281,
            "c": 78
          },
          "4": {
            "p": 0.1413217742355333,
            "c": 50
          },
          "5": {
            "p": 0.12485190760585173,
            "c": 44
          },
          "6": {
            "p": 0.10328981662054328,
            "c": 37
          }
        },
        "caps": {
          "data": false,
          "panic": false,
          "corr": false
        },
        "flags": {
          "Icorr": 0,
          "Ipanic": 0,
          "Idefense": 1
        },
        "vec": [
          -0.2948377927363878,
          -0.2511194790392795,
          -1.1276806336159881,
          2.6811331195360566,
          -1.3703187683887121,
          -2.817648298182603
        ]
      }
    },
    "60D": {
      "featuresZ": {
        "x": -1.4037898190367537,
        "y": -0.988295333494391,
        "rates": -2.055227747437257,
        "usd": 2.711805548724712,
        "vix": -0.6694973559560808,
        "goldFear": -3.0003470644342727
      },
      "daily": {
        "score": 14,
        "Cfinal": 80,
        "regime7": "7C",
        "probs": {
          "1": {
            "p": 0.18772997365805724,
            "c": 47
          },
          "2": {
            "p": 0.3218561941410004,
            "c": 80
          },
          "3": {
            "p": 0.1399631278807097,
            "c": 35
          },
          "4": {
            "p": 0.1420940689045343,
            "c": 35
          },
          "5": {
            "p": 0.1078460192313161,
            "c": 27
          },
          "6": {
            "p": 0.10051061618438224,
            "c": 25
          }
        },
        "caps": {
          "data": false,
          "panic": false,
          "corr": false
        },
        "flags": {
          "Icorr": 0,
          "Ipanic": 0,
          "Idefense": 1
        },
        "vec": [
          -1.4037898190367537,
          -0.988295333494391,
          -2.055227747437257,
          2.711805548724712,
          -0.6694973559560808,
          -3.0003470644342727
        ]
      }
    },
    "252D": {
      "featuresZ": {
        "x": -0.09290498716475099,
        "y": -0.38516396112135887,
        "rates": -1.0976287354713845,
        "usd": 1.550493697661166,
        "vix": -0.49145908461993637,
        "goldFear": -1.6981992116014246
      },
      "daily": {
        "score": 6,
        "Cfinal": 78,
        "regime7": "7C",
        "probs": {
          "1": {
            "p": 0.17464051748295356,
            "c": 60
          },
          "2": {
            "p": 0.2272029223999252,
            "c": 78
          },
          "3": {
            "p": 0.2016494699019724,
            "c": 69
          },
          "4": {
            "p": 0.1581075409993181,
            "c": 54
          },
          "5": {
            "p": 0.13320328611032925,
            "c": 46
          },
          "6": {
            "p": 0.10519626310550151,
            "c": 36
          }
        },
        "caps": {
          "data": false,
          "panic": false,
          "corr": false
        },
        "flags": {
          "Icorr": 0,
          "Ipanic": 0,
          "Idefense": 1
        },
        "vec": [
          -0.09290498716475099,
          -0.38516396112135887,
          -1.0976287354713845,
          1.550493697661166,
          -0.49145908461993637,
          -1.6981992116014246
        ]
      }
    }
  },
  "dataHealth": {
    "level": "OK",
    "source": "yfinance"
  },
  "latencyMin": 933.2,
  "fetchedAt": "2026-02-25T15:33:11.313077-05:00"
}